LICENSE
MANIFEST.in
README.rst
requirements.txt
setup.cfg
setup.py
WeAppRobot.egg-info/PKG-INFO
WeAppRobot.egg-info/SOURCES.txt
WeAppRobot.egg-info/dependency_links.txt
WeAppRobot.egg-info/requires.txt
WeAppRobot.egg-info/top_level.txt
weapprobot/__init__.py
weapprobot/client.py
weapprobot/config.py
weapprobot/exceptions.py
weapprobot/logger.py
weapprobot/parser.py
weapprobot/pay.py
weapprobot/replies.py
weapprobot/robot.py
weapprobot/testing.py
weapprobot/utils.py
weapprobot/contrib/__init__.py
weapprobot/contrib/bottle.py
weapprobot/contrib/django.py
weapprobot/contrib/error.html
weapprobot/contrib/flask.py
weapprobot/contrib/tornado.py
weapprobot/crypto/__init__.py
weapprobot/crypto/exceptions.py
weapprobot/crypto/pkcs7.py
weapprobot/messages/__init__.py
weapprobot/messages/base.py
weapprobot/messages/entries.py
weapprobot/messages/events.py
weapprobot/messages/messages.py
weapprobot/session/__init__.py
weapprobot/session/filestorage.py
weapprobot/session/mongodbstorage.py
weapprobot/session/mysqlstorage.py
weapprobot/session/redisstorage.py
weapprobot/session/saekvstorage.py
weapprobot/session/sqlitestorage.py